<caption>
<formalpara>
<title>Figure 6. A gene with SL2 trans-splicing at the second exon.</title>
<para>The picture shows portions of two operon genes, <emphasis><ulink url="http://www.wormbase.org/db/get?name=WBGene00006968;class=Gene" role="_blank">yars-1</ulink></emphasis> and <emphasis><ulink url="http://www.wormbase.org/db/get?name=WBGene00019543;class=Gene" role="_blank">cif-1</ulink></emphasis>, with the region between them. The numbers of SL1 and SL2 reads (<link linkend="bib1">Allen et al., 2011</link><!--: PMID 21177958-->) are given at the sites of trans-splicing. Mapped ESTs are shown as green bars. Some contain exon 1, whereas others begin with trans-splicing at exon 2.</para>
</formalpara>
</caption>